tAI/.env
tAI/KeyAutomation.py
tAI/__init__.py
tAI/__main__.py
tAI/config.json
tAI/main.py
tAI/secret.key
tAI/App/__init__.py
tAI/App/app.py
tAI/App/models.py
tAI/App/style.tcss
tAI/LLM/LLM_Integration.py
tAI/LLM/__init__.py
tAI/LLM/prompt.py
tAI/Utils/API.py
tAI/Utils/__init__.py
tAI/Utils/api_key_manager.py
tAI/Utils/config_manager.py
tAI/Utils/security.py
tai_textual-1.0.2.dist-info/licenses/LICENSE
tai_textual-1.0.2.dist-info/METADATA
tai_textual-1.0.2.dist-info/WHEEL
tai_textual-1.0.2.dist-info/entry_points.txt
tai_textual-1.0.2.dist-info/top_level.txt
tai_textual-1.0.2.dist-info/RECORD
