Metadata-Version: 2.4
Name: tai-textual
Version: 1.0.2
Summary: tAI is a tool that helps you to find the right command.
Author: Shoaib
Author-email: shoaib8@gmail.com>
Project-URL: Bug Tracker, https://github.com/KillerShoaib/tAI/issues
Project-URL: Source Code, https://github.com/KillerShoaib/tAI
Classifier: Programming Language :: Python :: 3.12
Classifier: License :: OSI Approved :: MIT License
Classifier: Operating System :: OS Independent
Classifier: Development Status :: 5 - Production/Stable
Classifier: Environment :: Console
Classifier: Intended Audience :: Developers
Classifier: Topic :: Software Development :: Libraries :: Python Modules
Classifier: Topic :: Terminals
Classifier: Topic :: Utilities
Requires-Python: >=3.12
License-File: LICENSE
Requires-Dist: aiohappyeyeballs==2.6.1
Requires-Dist: aiohttp==3.12.13
Requires-Dist: aiosignal==1.3.2
Requires-Dist: annotated-types==0.7.0
Requires-Dist: anyio==4.9.0
Requires-Dist: attrs==25.3.0
Requires-Dist: cachetools==5.5.2
Requires-Dist: certifi==2025.1.31
Requires-Dist: cffi==1.17.1
Requires-Dist: charset-normalizer==3.4.2
Requires-Dist: click==8.2.1
Requires-Dist: cryptography==45.0.5
Requires-Dist: distro==1.9.0
Requires-Dist: docutils==0.21.2
Requires-Dist: evdev==1.9.2
Requires-Dist: filelock==3.18.0
Requires-Dist: frozenlist==1.7.0
Requires-Dist: fsspec==2025.5.1
Requires-Dist: google-auth==2.40.2
Requires-Dist: google-genai==1.17.0
Requires-Dist: h11==0.14.0
Requires-Dist: hf-xet==1.1.5
Requires-Dist: httpcore==1.0.8
Requires-Dist: httpx==0.28.1
Requires-Dist: huggingface-hub==0.33.1
Requires-Dist: id==1.5.0
Requires-Dist: idna==3.10
Requires-Dist: importlib_metadata==8.7.0
Requires-Dist: jaraco.classes==3.4.0
Requires-Dist: jaraco.context==6.0.1
Requires-Dist: jaraco.functools==4.2.1
Requires-Dist: jeepney==0.9.0
Requires-Dist: Jinja2==3.1.6
Requires-Dist: jiter==0.10.0
Requires-Dist: jsonschema==4.24.0
Requires-Dist: jsonschema-specifications==2025.4.1
Requires-Dist: keyring==25.6.0
Requires-Dist: linkify-it-py==2.0.3
Requires-Dist: litellm==1.73.1
Requires-Dist: markdown-it-py==3.0.0
Requires-Dist: MarkupSafe==3.0.2
Requires-Dist: mdit-py-plugins==0.4.2
Requires-Dist: mdurl==0.1.2
Requires-Dist: more-itertools==10.7.0
Requires-Dist: multidict==6.5.1
Requires-Dist: nh3==0.2.21
Requires-Dist: openai==1.91.0
Requires-Dist: ordered-set==4.1.0
Requires-Dist: packaging==25.0
Requires-Dist: platformdirs==4.3.7
Requires-Dist: prompt_toolkit==3.0.51
Requires-Dist: propcache==0.3.2
Requires-Dist: pyasn1==0.6.1
Requires-Dist: pyasn1_modules==0.4.2
Requires-Dist: pycparser==2.22
Requires-Dist: pydantic==2.11.5
Requires-Dist: pydantic_core==2.33.2
Requires-Dist: Pygments==2.19.1
Requires-Dist: pynput==1.8.1
Requires-Dist: python-dotenv==1.1.0
Requires-Dist: python-xlib==0.33
Requires-Dist: PyYAML==6.0.2
Requires-Dist: readme_renderer==44.0
Requires-Dist: referencing==0.36.2
Requires-Dist: regex==2024.11.6
Requires-Dist: requests==2.32.3
Requires-Dist: requests-toolbelt==1.0.0
Requires-Dist: rfc3986==2.0.0
Requires-Dist: rich==14.0.0
Requires-Dist: rpds-py==0.25.1
Requires-Dist: rsa==4.9.1
Requires-Dist: SecretStorage==3.3.3
Requires-Dist: setuptools==80.9.0
Requires-Dist: six==1.17.0
Requires-Dist: sniffio==1.3.1
Requires-Dist: textual==3.1.0
Requires-Dist: tiktoken==0.9.0
Requires-Dist: tokenizers==0.21.2
Requires-Dist: tqdm==4.67.1
Requires-Dist: twine==6.1.0
Requires-Dist: typing-inspection==0.4.1
Requires-Dist: typing_extensions==4.13.2
Requires-Dist: uc-micro-py==1.0.3
Requires-Dist: urllib3==2.4.0
Requires-Dist: wcwidth==0.2.13
Requires-Dist: websockets==15.0.1
Requires-Dist: wheel==0.45.1
Requires-Dist: yarl==1.20.1
Requires-Dist: zipp==3.23.0
Requires-Dist: zstandard==0.23.0
Dynamic: author
Dynamic: author-email
Dynamic: classifier
Dynamic: description
Dynamic: description-content-type
Dynamic: license-file
Dynamic: project-url
Dynamic: requires-dist
Dynamic: requires-python
Dynamic: summary
